{
    "loc_grocery": {
        "name": "Local Grocery",
        "source_id": "wi_local_grocery",
        "url": "mapbox://wodacooper.wi_local_grocery_stores",
        "source_layer": "hello_world",
        "layout": {
            "visibility": "none"
        },
        "visible": false,
        "circle": {
            "circle-color": "#00ff00",
            "circle-radius": 5,
            "circle-stroke-color": "#ffffff",
            "circle-stroke-width": 2
        },
        "hover": {
            "Name": [
                true,
                ""
            ],
            "Street Address": [
                true,
                ""
            ],
            "County": [
                true,
                ""
            ],
            "City": [
                true,
                ""
            ]
        },
        "click": {
           "Name": [
                true,
                ""
            ],
            "Street Address": [
                true,
                ""
            ],
            "County": [
                true,
                ""
            ],
            "City": [
                true,
                ""
            ],
            "Zip Code": [
                true,
                ""
            ]
        }
    },
    "qct_dda": {
        "name": "2026 QCT/DDAs",
        "source_id": "qct_dda_26_source",
        "url": "mapbox://wodacooper.qct_dda_26",
        "source_layer": "hello_world",
        "layout": {
            "visibility": "none"
        },
        "visible": false,
        "perm_filters":[["==","state", 55]],

        "fill": {
            "fill-color": [
                    "match",
                    ["get", "zone"],
                    "qct_only",
                    "#ffffff",
                    "dda_only",
                    "#a0a0a0",
                    "both",
                    "#ffa500",
                    "#000000"
                ],
            "fill-opacity": 
                [
                    "match",
                    ["get", "zone"],
                    "neither",
                    0,
                    0.65
                ]
                
        },
        "legend": [
            [
                "QCT and DDA",
                "#ffa500"
            ],
           [
                "QCT",
                "#ffffff"
            ],
            [
                "DDA",
                "#a0a0a0"
            ]
        ],
        "click":{
            "zone":[true,""],
            "VLIL_60%":[true,""],
            "FMR":[true,""],
            "Rent_Limit":[true,""]
        },
        "hover": {
            "zone": [
                true,
                ""
            ]
        }
    },
    

    "test_w": {
        "name": "2027 Test Score With County Bonus",
        "source_id": "wi_test_w",
        "url": "mapbox://wodacooper.wi_test",
        "source_layer": "hello_world",
        "layout": {
            "visibility": "visible"
        },
        "visible": true,
        "line": {
            "line-opacity": [
                "match",
                [
                    "get",
                    "potential>25"
                ],
                "yes",
                1,
                0
            ],
            "line-width": 2,
            "line-color": "#000000"
        },
        "fill": {
            "fill-color": [
                "step",
                [
                    "get",
                    "score_w"
                ],
                "#ffffff",
                33,
                "#70534e",
                34,
                "#346b36",
                35,
                "#0000ff",
                36,
                "#ff0000",
                37,
                "#fe8103",
                38,
                "#ffff00",
                39,
                "#ff00ff",
                40,
                "#00ff00",
                41,
                "#00ffff"
            ],
            "fill-opacity": [
                "step",
                [
                    "get",
                    "score_w"
                ],
                0,
                25,
                0.6
            ]
        },
        "cat_filters": {
            "project_in_county": "Project in County",
            "Set-Aside": "Set-Aside"
        },
        "num_filters": {
            "score_w": "Score with County Bonus",
            "aeo_score": "Area of Economic Opportunity Score"
        },
        "legend": [
            [
                "41",
                "#00ffff"
            ],
            [
                "40",
                "#00ff00"
            ],
            [
                "39",
                "#ff00ff"
            ],
            [
                "38",
                "#ffff00"
            ],
            [
                "37",
                "#fe8103"
            ],
            [
                "36",
                "#ff0000"
            ],
            [
                "35",
                "#0000ff"
            ],
            [
                "34",
                "#346b36"
            ],
            [
                "33",
                "#70534e"
            ],
            [
                "25-32",
                "#ffffff"
            ],
            [
                "potential>25",
                "#000000"
            ]
        ],
        "hover": {
            "Name": [
                true,
                "county"
            ],
             "score_w": [
                true,
                ""
            ],
            "aeo_score": [
                true,
                "Area of Economic Opportunity Score"
            ],
            "job_pts":[
                true,
                "Job Score"
            ],
            "Set-Aside":[
                true,
                ""
            ]
        },

        "click": {
            "Name": [
                true,
                "county"
            ],
            "score": [
                true,
                ""
            ],
            "aeo_score": [
                true,
                "Area of Economic Opportunity Score"
            ],
            
            "med_inc_pts": [
                true,
                ""
            ],
            "rent_bur_pts": [
                true,
                ""
            ],
            "SD_pts": [
                true,
                ""
            ],
            "job_pts":[
                true,
                "Job Score"
            ],
            "job_center_pts": [
                true,
                ""
            ],
            "job_growth_pts": [
                true,
                ""
            ],
            "Set-Aside":[
                true,
                ""
            ],
            "Field5": [
                true,
                "SD_name"
            ],
            "project_in_county":[
                true,
                ""
            ]
        },
        "cat_filter_vals": {
            "project_in_county": [
                "yes",
                "no"
            ],
            "Set-Aside": [
                "Metro",
                "Non-Metro"
            ]
        },
        "num_filter_vals": {
            "score_w": [
                0.0,
                41.0
            ],
            "aeo_score": [
                0.0,
                36.0
            ]
        }
    },
    "test": {
        "name": "2027 Test Score",
        "source_id": "wi_test_source",
        "url": "mapbox://wodacooper.wi_test",
        "source_layer": "hello_world",
        "layout": {
            "visibility": "visible"
        },
        "visible": true,
        "line": {
            "line-opacity": [
                "match",
                [
                    "get",
                    "potential>25"
                ],
                "yes",
                1,
                0
            ],
            "line-width": 2,
            "line-color": "#000000"
        },
        "fill": {
            "fill-color": [
                "step",
                [
                    "get",
                    "score"
                ],
                "#ffffff",
                23,
                "#70534e",
                28,
                "#346b36",
                30,
                "#0000ff",
                31,
                "#ff0000",
                32,
                "#fe8103",
                33,
                "#ffff00",
                34,
                "#ff00ff",
                35,
                "#00ff00",
                36,
                "#00ffff"
            ],
            "fill-opacity": [
                "step",
                [
                    "get",
                    "score"
                ],
                0,
                16,
                0.6
            ]
        },
        "cat_filters": {
            "project_in_county": "Project in County",
            "Set-Aside": "Set-Aside"
        },
        "num_filters": {
            "score": "Score",
            "aeo_score": "Area of Economic Opportunity Score"
        },
        "legend": [
            [
                "36",
                "#00ffff"
            ],
            [
                "35",
                "#00ff00"
            ],
            [
                "34",
                "#ff00ff"
            ],
            [
                "33",
                "#ffff00"
            ],
            [
                "32",
                "#fe8103"
            ],
            [
                "31",
                "#ff0000"
            ],
            [
                "30",
                "#0000ff"
            ],
            [
                "28-29",
                "#346b36"
            ],
            [
                "23-27",
                "#70534e"
            ],
            [
                "16-22",
                "#ffffff"
            ],
            [
                "potential>25",
                "#000000"
            ]
        ],
        "hover": {
            "Name": [
                true,
                "county"
            ],
             "score": [
                true,
                ""
            ],
            "aeo_score": [
                true,
                "Area of Economic Opportunity Score"
            ],
            "job_pts":[
                true,
                "Job Score"
            ],
            "Set-Aside":[
                true,
                ""
            ]
        },

        "click": {
            "Name": [
                true,
                "county"
            ],
            "score": [
                true,
                ""
            ],
            "aeo_score": [
                true,
                "Area of Economic Opportunity Score"
            ],
            
            "med_inc_pts": [
                true,
                ""
            ],
            "rent_bur_pts": [
                true,
                ""
            ],
            "SD_pts": [
                true,
                ""
            ],
            "job_pts":[
                true,
                "Job Score"
            ],
            "job_center_pts": [
                true,
                ""
            ],
            "job_growth_pts": [
                true,
                ""
            ],
            "Set-Aside":[
                true,
                ""
            ],
            "Field5": [
                true,
                "SD_name"
            ],
            "project_in_county":[
                true,
                ""
            ]
        },
        "cat_filter_vals": {
            "project_in_county": [
                "yes",
                "no"
            ],
            "Set-Aside": [
                "Metro",
                "Non-Metro"
            ]
        },
        "num_filter_vals": {
            "score": [
                0.0,
                41.0
            ],
            "aeo_score": [
                0.0,
                36.0
            ]
        }
    },
    "no_awards": {
        "name": "Counties Without Recent Award",
        "source_id": "wi_no_awards_source",
        "url": "mapbox://wodacooper.wi_no_awards",
        "source_layer": "hello_world",
        "layout": {
            "visibility": "none"
        },
        "visible": false,
        "fill": {
            "fill-color": [
                "match",
                [
                    "get",
                    "is_largest_city"
                ],
                "no",
                "#ffffff",
                "#fcae1e"
            ],
            "fill-opacity": 0.6
        },
        
        "legend": [
            [
                "County",
                "#ffffff"
            ],
            [
                "Largest City in County",
                "#fcae1e"
            ]
        ],
        "hover": {
            "County": [
                true,
                "county"
            ],
            "County_pop":[
                true,
                ""
            ],
            "City": [
                true,
                "Current City"
            ],
            "City_pop":[
                true,
                "Current City Pop"
            ],
            "Largest_City_Pop": [
                true,
                ""
            ]
            
        },

        "click": {
            "County": [
                true,
                ""
            ],
            "County_pop":[
                true,
                ""
            ],
            "City": [
                true,
                "Current City"
            ],
            "City_pop":[
                true,
                "Current City Pop"
            ],
            "Largest_City":[
                true,
                "Largest City in County"
            ],
            "Largest_City_Pop": [
                true,
                "Largest City Pop"
            ]
        }
    }

}
